{
    "metadata": {
        "ocr_model": "PP-OCRv5_mobile",
        "python_version": "3.13.7",
        "libraries": {
            "pdf2image": "1.17.0",
            "paddleocr": "3.2.0",
            "Pillow": "11.3.0",
            "psutil": "7.1.0",
            "cpuinfo": "9.0.0"
        },
        "system": {
            "platform": "Windows-11-10.0.26100-SP0",
            "cpu": "Intel(R) Core(TM) i7-8700 CPU @ 3.20GHz",
            "cpu_count": 12,
            "total_memory_mb": 16163.2890625,
            "poppler_path": "C:\\Users\\rmander\\Documents\\poppler-25.07.0\\Library\\bin"
        },
        "timing": {
            "document_start_time": 1761155929.4997613,
            "document_end_time": 1761155950.9826133,
            "total_time_seconds": 21.4828519821167,
            "per_page_seconds": {
                "Metamorphosis_page_1": 8.677088499069214,
                "Metamorphosis_page_2": 12.60348105430603
            }
        },
        "resource_usage": {
            "per_page": {
                "cpu_percent": {
                    "Metamorphosis_page_1": 100.0,
                    "Metamorphosis_page_2": 97.4
                },
                "memory_mb": {
                    "Metamorphosis_page_1": {
                        "system_memory_mb": 12754.0546875,
                        "process_memory_mb": 768.21875
                    },
                    "Metamorphosis_page_2": {
                        "system_memory_mb": 12780.546875,
                        "process_memory_mb": 969.23828125
                    }
                }
            },
            "document": {
                "avg_cpu_percent": 98.7,
                "max_cpu_percent": 100.0,
                "avg_process_memory_mb": 868.728515625,
                "max_process_memory_mb": 969.23828125
            }
        }
    },
    "results": {
        "Metamorphosis_page_1": [
            "Metamorphosis",
            "by Franz Kafka",
            "Translated by David Wyllie",
            "Prepared and Published by:",
            "FDD",
            "E-BooksDirectory.com"
        ],
        "Metamorphosis_page_2": [
            "I",
            "One morning, when Gregor Samsa woke from troubled",
            "dreams, he found himself transformed in his bed into a",
            "horrible vermin. He lay on his armour-like back, and if he",
            "lifted his head a little he could see his brown belly,",
            "slightly domed and divided by arches into stiff sections.",
            "The bedding was hardly able to cover it and seemed",
            "ready to slide off any moment. His many legs, pitifully",
            "thin compared with the size of the rest of him, waved",
            "about helplessly as he looked.",
            "\"What's happened to me?\" he thought. It wasn't a",
            "dream. His room, a proper human room although a little",
            "too small, lay peacefully between its four familiar walls.",
            "A collection of textile samples lay spread out on the table",
            "- Samsa was a travelling salesman - and above it there",
            "hung a picture that he had recently cut out of an",
            "illustrated magazine and housed in a nice, gilded frame.",
            "It showed a lady fitted out with a fur hat and fur boa",
            "who sat upright, raising a heavy fur muff that covered",
            "the whole of her lower arm towards the viewer.",
            "Gregor then turned to look out the window at the dull",
            "weather. Drops of rain could be heard hitting the pane,",
            "which made him feel quite sad. \"How about if I sleep a",
            "little bit longer and forget all this nonsense\", he thought,",
            "but that was something he was unable to do because he",
            "was used to sleeping on his right, and in his present state",
            "couldn't get into that position. However hard he threw",
            "himself onto his right, he always rolled back to where he",
            "was. He must have tried it a hundred times, shut his eyes",
            "so that he wouldn't have to look at the floundering legs,"
        ]
    }
}